checui_sales/sales.py
checui_sales/settings.py
checui_sales-0.0.1.dist-info/METADATA
checui_sales-0.0.1.dist-info/WHEEL
checui_sales-0.0.1.dist-info/RECORD
