Metadata-Version: 2.1
Name: checui_sales
Version: 0.0.1
Summary: My customized ORM on Sales
Project-URL: Homepage, https://github.com/Checui/IBD_ticket
Project-URL: Bug Tracker, https://github.com/Checui/IBD_ticket/issues
Author-email: checui <che.cui@upm.es>
Classifier: License :: OSI Approved :: MIT License
Classifier: Operating System :: OS Independent
Classifier: Programming Language :: Python :: 3
Requires-Python: >=3.9
